mpscli/__init__.py
mpscli/demo.py
mpscli/model/SConcept.py
mpscli/model/SLanguage.py
mpscli/model/SModel.py
mpscli/model/SNode.py
mpscli/model/SNodeRef.py
mpscli/model/SRepository.py
mpscli/model/SSolution.py
mpscli/model/__init__.py
mpscli/model/builder/NodeIdEncodingUtils.py
mpscli/model/builder/SLanguageBuilder.py
mpscli/model/builder/SModelBuilderBase.py
mpscli/model/builder/SModelBuilderDefaultPersistency.py
mpscli/model/builder/SModelBuilderFilePerRootPersistency.py
mpscli/model/builder/SSolutionBuilder.py
mpscli/model/builder/SSolutionsRepositoryBuilder.py
mpscli/model/builder/__init__.py
mps_cli-0.4.0.dist-info/METADATA
mps_cli-0.4.0.dist-info/WHEEL
mps_cli-0.4.0.dist-info/licenses/LICENSE
mps_cli-0.4.0.dist-info/RECORD
