Metadata-Version: 2.4
Name: mps-cli
Version: 0.4.0
Summary: MPS Command Line Interface (MPS-CLI) is a library to parse MPS files and build the model as Python objects.
Project-URL: Homepage, https://github.com/mbeddr/mps-cli
Project-URL: Bug Tracker, https://github.com/mbeddr/mps-cli/issues
Author-email: Daniel Ratiu <ratiud@googlemail.com>
License-File: LICENSE
Classifier: License :: OSI Approved :: Eclipse Public License 2.0 (EPL-2.0)
Classifier: Operating System :: OS Independent
Classifier: Programming Language :: Python :: 3
Requires-Python: >=3.7
